handwriting_sample/__init__.py
handwriting_sample/exceptions.py
handwriting_sample/interface.py
handwriting_sample/base/__init__.py
handwriting_sample/base/containers.py
handwriting_sample/base/utils.py
handwriting_sample/reader/__init__.py
handwriting_sample/reader/exceptions.py
handwriting_sample/reader/interface.py
handwriting_sample/reader/readers.py
handwriting_sample/transformer/__init__.py
handwriting_sample/transformer/exceptions.py
handwriting_sample/transformer/interface.py
handwriting_sample/validator/__init__.py
handwriting_sample/validator/exceptions.py
handwriting_sample/validator/interface.py
handwriting_sample/visualizer/__init__.py
handwriting_sample/visualizer/exceptions.py
handwriting_sample/visualizer/interface.py
handwriting_sample/writer/__init__.py
handwriting_sample/writer/exceptions.py
handwriting_sample/writer/interface.py
handwriting_sample/writer/writers.py
handwriting_sample-1.0.6.dist-info/licenses/LICENSE
handwriting_sample-1.0.6.dist-info/METADATA
handwriting_sample-1.0.6.dist-info/WHEEL
handwriting_sample-1.0.6.dist-info/top_level.txt
handwriting_sample-1.0.6.dist-info/RECORD
